README.md
pyproject.toml
setup.py
fds/__init__.py
fds/fds_cli.py
fds/fds_client_configuration.py
fds/fds_request.py
fds/fdscli_cli.py
fds/galaxy_fds_client.py
fds/galaxy_fds_client_exception.py
fds/test_utils.py
fds/utils.py
fds/auth/__init__.py
fds/auth/common.py
fds/auth/signature/__init__.py
fds/auth/signature/signer.py
fds/model/__init__.py
fds/model/access_control_policy.py
fds/model/copy_object_result.py
fds/model/fds_access_log_config.py
fds/model/fds_bucket.py
fds/model/fds_cors.py
fds/model/fds_lifecycle.py
fds/model/fds_object.py
fds/model/fds_object_listing.py
fds/model/fds_object_metadata.py
fds/model/fds_object_summary.py
fds/model/fds_storage_class.py
fds/model/init_multipart_upload_result.py
fds/model/list_domain_mappings_result.py
fds/model/permission.py
fds/model/put_object_result.py
fds/model/subresource.py
fds/model/timestamp_anti_stealing_link_config.py
fds/model/upload_part_result.py
fds/model/upload_part_result_list.py
galaxy_fds.egg-info/PKG-INFO
galaxy_fds.egg-info/SOURCES.txt
galaxy_fds.egg-info/dependency_links.txt
galaxy_fds.egg-info/entry_points.txt
galaxy_fds.egg-info/requires.txt
galaxy_fds.egg-info/top_level.txt
test/__init__.py
test/client_test.py
test/signer_test.py
test/testMultithreading.py
test/test_common.py
test/test_fdscli_cli.py